{"assets/icons/behance.svg":["assets/icons/behance.svg"],"assets/icons/check.svg":["assets/icons/check.svg"],"assets/icons/download.svg":["assets/icons/download.svg"],"assets/icons/dribble.svg":["assets/icons/dribble.svg"],"assets/icons/fb.png":["assets/icons/fb.png"],"assets/icons/fb.svg":["assets/icons/fb.svg"],"assets/icons/github.svg":["assets/icons/github.svg"],"assets/icons/linkedin.svg":["assets/icons/linkedin.svg"],"assets/icons/twitter.svg":["assets/icons/twitter.svg"],"assets/images/bg.jpeg":["assets/images/bg.jpeg"],"assets/images/display-Image.jpeg":["assets/images/display-Image.jpeg"],"assets/images/linkedInProfile.png":["assets/images/linkedInProfile.png"],"packages/cupertino_icons/assets/CupertinoIcons.ttf":["packages/cupertino_icons/assets/CupertinoIcons.ttf"],"packages/font_awesome_flutter/lib/fonts/fa-brands-400.ttf":["packages/font_awesome_flutter/lib/fonts/fa-brands-400.ttf"],"packages/font_awesome_flutter/lib/fonts/fa-regular-400.ttf":["packages/font_awesome_flutter/lib/fonts/fa-regular-400.ttf"],"packages/font_awesome_flutter/lib/fonts/fa-solid-900.ttf":["packages/font_awesome_flutter/lib/fonts/fa-solid-900.ttf"],"videos/CRUD.mp4":["videos/CRUD.mp4"],"videos/GoogleMapRoutes.mp4":["videos/GoogleMapRoutes.mp4"],"videos/StitchCraft.mp4":["videos/StitchCraft.mp4"],"videos/covid.mp4":["videos/covid.mp4"],"videos/ecommerce.mp4":["videos/ecommerce.mp4"],"videos/movieinfo.mp4":["videos/movieinfo.mp4"],"videos/payment.mp4":["videos/payment.mp4"],"videos/socialmedia.mp4":["videos/socialmedia.mp4"]}